README.md
setup.py
caspi/__init__.py
caspi/cu.py
caspi/gs25.py
caspi/seven_eleven.py
caspi/util.py
caspi.egg-info/PKG-INFO
caspi.egg-info/SOURCES.txt
caspi.egg-info/dependency_links.txt
caspi.egg-info/requires.txt
caspi.egg-info/top_level.txt