Metadata-Version: 1.0
Name: caspi
Version: 0.1
Summary: Korean CStore API
Home-page: https://github.com/DSMdongly/Caspi
Author: Toygrammer
Author-email: gdh0608@naver.com
License: MIT
Platform: UNKNOWN
